Metadata-Version: 2.1
Name: hypervigilantnessz
Version: 1.1
Summary: hypervigilantnessz
Home-page: https://github.com/mirukutea/hypervigilantnessz
Download-URL: https://github.com/mirukutea/hypervigilantnessz/archive/v_01.tar.gz
Author: Mirukutea
Author-email: tea@masrizky.com
License: MIT
Project-URL: Documentation, https://github.com/mirukutea/hypervigilantnessz
Project-URL: Funding, https://donate.pypi.org
Project-URL: Say Thanks!, http://saythanks.io/to/example
Project-URL: Source, https://github.com/mirukutea/hypervigilantnessz/
Project-URL: Tracker, https://github.com/mirukutea/hypervigilantnessz/issues
Keywords: SOME,MEANINGFULL,KEYWORDS
Classifier: Development Status :: 3 - Alpha
Classifier: Intended Audience :: Developers
Classifier: Topic :: Software Development :: Build Tools
Classifier: License :: OSI Approved :: MIT License
Classifier: Programming Language :: Python :: 3
Classifier: Programming Language :: Python :: 3.4
Classifier: Programming Language :: Python :: 3.5
Classifier: Programming Language :: Python :: 3.6
License-File: LICENSE
Requires-Dist: validators
Requires-Dist: beautifulsoup4
Requires-Dist: discordautochat
Requires-Dist: discorudo
